mux.v
module alu8 (
    input wire [7:0] a,
    input wire [7:0] b,
    input wire [2:0] op,
    output reg [7:0]  y,
    output reg zero,
    output reg carry,
    output reg overflow
);
    always @(*) begin
        case(op)
            3'b000: {carry, y} = a + b;
            3'b001: {carry, y} = a - b;
            3'b011: y = a & b;
            3'b010: y = a | b;
            3'b100: y = a ^ b;
            3'b101: y = ~a;
            3'b110: y = a << 1;
            3'b111: y = a >> 1;
            default: y = 8'b0;
        endcase

        // Set carry and overflow for add/sub only
        if (op == 3'b000) begin
            overflow = (~a[7] & ~b[7] & y[7]) | (a[7] & b[7] & ~y[7]);
        end else if (op == 3'b001) begin
            overflow = (~a[7] & b[7] & y[7]) | (a[7] & ~b[7] & ~y[7]);
        end else begin
            carry = 0;
            overflow = 0;
        end

        zero = (y == 8'b0);
    end
endmodule

mux_tb.v
`timescale 1ns / 1ps

module alu8_tb;

    reg  [7:0] a, b;
    reg  [2:0] op;
    wire [7:0] y;
    wire       zero, carry, overflow;

    alu8 uut (
        .a(a),
        .b(b),
        .op(op),
        .y(y),
        .zero(zero),
        .carry(carry),
        .overflow(overflow)
    );

    initial begin
        $dumpfile("alu8.vcd");
        $dumpvars(0, alu8_tb);

        // Test Addition
        a = 8'd15; b = 8'd10; op = 3'b000; #10;
        a = 8'd200; b = 8'd100; op = 3'b000; #10;

        // Test Subtraction
        a = 8'd50; b = 8'd20; op = 3'b001; #10;
        a = 8'd20; b = 8'd50; op = 3'b001; #10;

        // Test AND
        a = 8'b10101010; b = 8'b11001100; op = 3'b011; #10;

        // Test OR
        a = 8'b10101010; b = 8'b11001100; op = 3'b010; #10;

        // Test XOR
        a = 8'b10101010; b = 8'b11001100; op = 3'b100; #10;

        // Test NOT
        a = 8'b10101010; b = 8'b00000000; op = 3'b101; #10;

        // Test Shift Left
        a = 8'b00001111; b = 8'b00000000; op = 3'b110; #10;

        // Test Shift Right
        a = 8'b11110000; b = 8'b00000000; op = 3'b111; #10;

        $finish;
    end

    initial begin
        $monitor("time=%0t a=%b b=%b op=%b | y=%b zero=%b carry=%b overflow=%b",
                 $time, a, b, op, y, zero, carry, overflow);
    end

endmodule

alu8.vcd
$date
	Thu Oct  9 18:12:18 2025
$end
$version
	Icarus Verilog
$end
$timescale
	1ps
$end
$scope module alu8_tb $end
$var wire 1 ! zero $end
$var wire 8 " y [7:0] $end
$var wire 1 # overflow $end
$var wire 1 $ carry $end
$var reg 8 % a [7:0] $end
$var reg 8 & b [7:0] $end
$var reg 3 ' op [2:0] $end
$scope module uut $end
$var wire 8 ( a [7:0] $end
$var wire 8 ) b [7:0] $end
$var wire 3 * op [2:0] $end
$var reg 1 $ carry $end
$var reg 1 # overflow $end
$var reg 8 + y [7:0] $end
$var reg 1 ! zero $end
$upscope $end
$upscope $end
$enddefinitions $end
$comment Show the parameter values. $end
$dumpall
$end
#0
$dumpvars
b11001 +
b0 *
b1010 )
b1111 (
b0 '
b1010 &
b1111 %
0$
0#
b11001 "
0!
$end
#10000
1$
b101100 "
b101100 +
b1100100 &
b1100100 )
b11001000 %
b11001000 (
#20000
0$
b11110 "
b11110 +
b1 '
b1 *
b10100 &
b10100 )
b110010 %
b110010 (
#30000
1$
b11100010 "
b11100010 +
b110010 &
b110010 )
b10100 %
b10100 (
#40000
0$
b10001000 "
b10001000 +
b11 '
b11 *
b11001100 &
b11001100 )
b10101010 %
b10101010 (
#50000
b11101110 "
b11101110 +
b10 '
b10 *
#60000
b1100110 "
b1100110 +
b100 '
b100 *
#70000
b1010101 "
b1010101 +
b101 '
b101 *
b0 &
b0 )
#80000
b11110 "
b11110 +
b110 '
b110 *
b1111 %
b1111 (
#90000
b1111000 "
b1111000 +
b111 '
b111 *
b11110000 %
b11110000 (
